{
  "artifact": "flux_stationarity_segment_report",
  "classification": {
    "flux_mean_mechanism": "mean_flux_imbalance_tail_drift",
    "outlet_cv_mechanism": "true_outlet_stationarity_oscillation"
  },
  "figure29_3_parity_claim_allowed": false,
  "fluent_validation_claim_allowed": false,
  "fsi_validation_claim_allowed": false,
  "hard_gate_tail_cv_limit": 0.1,
  "hard_gate_tail_mean_limit": 0.1,
  "new_lbm_run_executed": false,
  "new_parameter_tuning_executed": false,
  "production_readiness_claim_allowed": false,
  "quasi2d_validation_claim_allowed": false,
  "segments": [
    {
      "end_step": 100.0,
      "metrics": {
        "flux_imbalance_rel": {
          "available": true,
          "count": 11,
          "cv": 0.42602346224177823,
          "final": 0.2616487690818848,
          "max": 0.9604682988179245,
          "max_abs": 0.9604682988179245,
          "mean": 0.6335682168278574,
          "min": 0.0,
          "slope_per_step": -0.0014076705590213504,
          "std": 0.26991492529935346
        },
        "inlet_flux": {
          "available": true,
          "count": 11,
          "cv": 0.6101202546706413,
          "final": 43.76074485117861,
          "max": 43.916457281288984,
          "max_abs": 43.916457281288984,
          "mean": 24.62677745139995,
          "min": 0.0,
          "slope_per_step": 0.472037244257051,
          "std": 15.025295730365345
        },
        "midplane_flux": {
          "available": true,
          "count": 11,
          "cv": 1.1891149545371045,
          "final": 37.92058044172272,
          "max": 37.92058044172272,
          "max_abs": 37.92058044172272,
          "mean": 11.19196184081338,
          "min": 0.0,
          "slope_per_step": 0.38725210009749306,
          "std": 13.308529195519812
        },
        "midplane_to_inlet_flux_ratio": {
          "available": true,
          "count": 10,
          "cv": 0.9963028739404458,
          "final": 0.8665433042943602,
          "max": 0.8665433042943602,
          "max_abs": 0.8665433042943602,
          "mean": 0.31019642104570033,
          "min": 0.0,
          "slope_per_step": 0.010355318448784744,
          "std": 0.3090495857738718
        },
        "near_outlet_to_outlet_flux_ratio": {
          "available": true,
          "count": 11,
          "cv": 0.35061889713213956,
          "final": 1.0083619556893848,
          "max": 1.0083619556893848,
          "max_abs": 1.0083619556893848,
          "mean": 0.8192664306835276,
          "min": 0.0,
          "slope_per_step": 0.0068039762765145315,
          "std": 0.2872502923836429
        },
        "outlet_flux": {
          "available": true,
          "count": 11,
          "cv": 1.024640153542756,
          "final": 32.3107998267613,
          "max": 32.3107998267613,
          "max_abs": 32.3107998267613,
          "mean": 9.48066332176987,
          "min": 0.0,
          "slope_per_step": 0.28179119636641886,
          "std": 9.714268321705454
        },
        "outlet_flux_after_correction": {
          "available": true,
          "count": 11,
          "cv": 1.024640153542756,
          "final": 32.3107998267613,
          "max": 32.3107998267613,
          "max_abs": 32.3107998267613,
          "mean": 9.48066332176987,
          "min": 0.0,
          "slope_per_step": 0.28179119636641886,
          "std": 9.714268321705454
        },
        "outlet_to_inlet_flux_ratio": {
          "available": true,
          "count": 10,
          "cv": 0.6259040870958967,
          "final": 0.7383512309181152,
          "max": 0.7383512309181152,
          "max_abs": 0.7383512309181152,
          "mean": 0.3030749614893569,
          "min": 0.03953170118207541,
          "slope_per_step": 0.006100682190880849,
          "std": 0.18969585709262002
        }
      },
      "name": "0_100",
      "record_count": 11,
      "start_step": 0.0
    },
    {
      "end_step": 200.0,
      "metrics": {
        "flux_imbalance_rel": {
          "available": true,
          "count": 11,
          "cv": 0.4124890755310769,
          "final": 0.18087974336724078,
          "max": 0.3440477133887042,
          "max_abs": 0.3440477133887042,
          "mean": 0.22278987347964627,
          "min": 0.0475216343641737,
          "slope_per_step": 0.0012296686773616255,
          "std": 0.09189838894930487
        },
        "inlet_flux": {
          "available": true,
          "count": 11,
          "cv": 0.014122597260604457,
          "final": 41.943697539087225,
          "max": 43.76074485117861,
          "max_abs": 43.76074485117861,
          "mean": 42.95653116153207,
          "min": 41.943697539087225,
          "slope_per_step": -0.018826892432117028,
          "std": 0.6066577893069228
        },
        "midplane_flux": {
          "available": true,
          "count": 11,
          "cv": 0.1481045295706683,
          "final": 56.198060797684136,
          "max": 65.72804967763867,
          "max_abs": 65.72804967763867,
          "mean": 57.51592273514665,
          "min": 37.92058044172272,
          "slope_per_step": 0.16309278148067852,
          "std": 8.5183686795118
        },
        "midplane_to_inlet_flux_ratio": {
          "available": true,
          "count": 11,
          "cv": 0.15319269150808656,
          "final": 1.3398451756742071,
          "max": 1.5255159523057769,
          "max_abs": 1.5255159523057769,
          "mean": 1.3404996670545182,
          "min": 0.8665433042943602,
          "slope_per_step": 0.004335578786389552,
          "std": 0.20535475196177555
        },
        "near_outlet_to_outlet_flux_ratio": {
          "available": true,
          "count": 11,
          "cv": 0.005463000553238194,
          "final": 1.0001438087479524,
          "max": 1.0173348052985167,
          "max_abs": 1.0173348052985167,
          "mean": 1.011882247388867,
          "min": 1.0001438087479524,
          "slope_per_step": -0.00010787068443553433,
          "std": 0.005527913277297287
        },
        "outlet_flux": {
          "available": true,
          "count": 11,
          "cv": 0.18645825671332142,
          "final": 51.20578718381284,
          "max": 65.45242040478726,
          "max_abs": 65.45242040478726,
          "mean": 52.77516563429676,
          "min": 32.3107998267613,
          "slope_per_step": 0.21014818255314002,
          "std": 9.840365381927764
        },
        "outlet_flux_after_correction": {
          "available": true,
          "count": 11,
          "cv": 0.18645825671332142,
          "final": 51.20578718381284,
          "max": 65.45242040478726,
          "max_abs": 65.45242040478726,
          "mean": 52.77516563429676,
          "min": 32.3107998267613,
          "slope_per_step": 0.21014818255314002,
          "std": 9.840365381927764
        },
        "outlet_to_inlet_flux_ratio": {
          "available": true,
          "count": 11,
          "cv": 0.19234901278983252,
          "final": 1.2208219634450277,
          "max": 1.5245011266994486,
          "max_abs": 1.5245011266994486,
          "mean": 1.230544170182785,
          "min": 0.7383512309181152,
          "slope_per_step": 0.005378745467059191,
          "std": 0.23669395632894236
        }
      },
      "name": "100_200",
      "record_count": 11,
      "start_step": 100.0
    },
    {
      "end_step": 250.0,
      "metrics": {
        "flux_imbalance_rel": {
          "available": true,
          "count": 6,
          "cv": 0.5811986445433364,
          "final": 0.12846874691497526,
          "max": 0.18087974336724078,
          "max_abs": 0.18087974336724078,
          "mean": 0.0965984567837492,
          "min": 0.02417691648565375,
          "slope_per_step": -0.001810839615159163,
          "std": 0.056142892147693094
        },
        "inlet_flux": {
          "available": true,
          "count": 6,
          "cv": 0.0008834343737127037,
          "final": 42.00721999331026,
          "max": 42.00721999331026,
          "max_abs": 42.00721999331026,
          "mean": 41.937192453324464,
          "min": 41.898926254411606,
          "slope_per_step": 0.001397835458127312,
          "std": 0.03704875735027182
        },
        "midplane_flux": {
          "available": true,
          "count": 6,
          "cv": 0.26262790193732766,
          "final": 27.989709029053863,
          "max": 56.198060797684136,
          "max_abs": 56.198060797684136,
          "mean": 39.927164603134884,
          "min": 27.989709029053863,
          "slope_per_step": -0.6000307731193745,
          "std": 10.485987470027649
        },
        "midplane_to_inlet_flux_ratio": {
          "available": true,
          "count": 6,
          "cv": 0.26296511630443314,
          "final": 0.6663071022912558,
          "max": 1.3398451756742071,
          "max_abs": 1.3398451756742071,
          "mean": 0.952182964304898,
          "min": 0.6663071022912558,
          "slope_per_step": -0.01433324579854417,
          "std": 0.2503909039515374
        },
        "near_outlet_to_outlet_flux_ratio": {
          "available": true,
          "count": 6,
          "cv": 0.004702684756650543,
          "final": 0.9855689199996435,
          "max": 1.0001438087479524,
          "max_abs": 1.0001438087479524,
          "mean": 0.9934527560618306,
          "min": 0.9855689199996435,
          "slope_per_step": -0.00027030861965312794,
          "std": 0.004671895132384441
        },
        "outlet_flux": {
          "available": true,
          "count": 6,
          "cv": 0.10758125088374537,
          "final": 36.610605079387994,
          "max": 51.20578718381284,
          "max_abs": 51.20578718381284,
          "mean": 44.3288589826684,
          "min": 36.610605079387994,
          "slope_per_step": -0.277787872330563,
          "std": 4.768954099604619
        },
        "outlet_flux_after_correction": {
          "available": true,
          "count": 6,
          "cv": 0.10758125088374537,
          "final": 36.610605079387994,
          "max": 51.20578718381284,
          "max_abs": 51.20578718381284,
          "mean": 44.3288589826684,
          "min": 36.610605079387994,
          "slope_per_step": -0.277787872330563,
          "std": 4.768954099604619
        },
        "outlet_to_inlet_flux_ratio": {
          "available": true,
          "count": 6,
          "cv": 0.10809796240125301,
          "final": 0.8715312530850248,
          "max": 1.2208219634450277,
          "max_abs": 1.2208219634450277,
          "mean": 1.0570985129135675,
          "min": 0.8715312530850248,
          "slope_per_step": -0.00665488119152494,
          "std": 0.1142701953033513
        }
      },
      "name": "200_250",
      "record_count": 6,
      "start_step": 200.0
    },
    {
      "end_step": 300.0,
      "metrics": {
        "flux_imbalance_rel": {
          "available": true,
          "count": 6,
          "cv": 0.26561305526369366,
          "final": 0.28361880725240296,
          "max": 0.3583493754188707,
          "max_abs": 0.3583493754188707,
          "mean": 0.28983402505771905,
          "min": 0.12846874691497526,
          "slope_per_step": 0.0024014504572192137,
          "std": 0.0769837009149547
        },
        "inlet_flux": {
          "available": true,
          "count": 6,
          "cv": 0.007973017523285972,
          "final": 42.97505803732421,
          "max": 42.97505803732421,
          "max_abs": 42.97505803732421,
          "mean": 42.62287837656804,
          "min": 42.00721999331026,
          "slope_per_step": 0.019015787298426016,
          "std": 0.33983295618926374
        },
        "midplane_flux": {
          "available": true,
          "count": 6,
          "cv": 0.03787396247692953,
          "final": 30.094100030604615,
          "max": 30.094100030604615,
          "max_abs": 30.094100030604615,
          "mean": 27.8601477803582,
          "min": 26.98942993946515,
          "slope_per_step": 0.03577187684263385,
          "std": 1.055174191634998
        },
        "midplane_to_inlet_flux_ratio": {
          "available": true,
          "count": 6,
          "cv": 0.035860710323271504,
          "final": 0.7002689793802636,
          "max": 0.7002689793802636,
          "max_abs": 0.7002689793802636,
          "mean": 0.6536202759639698,
          "min": 0.6329315729213756,
          "slope_per_step": 0.0005409168658021591,
          "std": 0.0234392873777607
        },
        "near_outlet_to_outlet_flux_ratio": {
          "available": true,
          "count": 6,
          "cv": 0.00519196265204624,
          "final": 0.9907887424954328,
          "max": 0.9907887424954328,
          "max_abs": 0.9907887424954328,
          "mean": 0.9829125284166428,
          "min": 0.9747990569059142,
          "slope_per_step": 0.00010963376399436659,
          "std": 0.005103245137767548
        },
        "outlet_flux": {
          "available": true,
          "count": 6,
          "cv": 0.10154913182322847,
          "final": 30.786523335175524,
          "max": 36.610605079387994,
          "max_abs": 36.610605079387994,
          "mean": 30.249632205668384,
          "min": 27.361227214205833,
          "slope_per_step": -0.08752527731194709,
          "std": 3.071823888457596
        },
        "outlet_flux_after_correction": {
          "available": true,
          "count": 6,
          "cv": 0.10154913182322847,
          "final": 30.786523335175524,
          "max": 36.610605079387994,
          "max_abs": 36.610605079387994,
          "mean": 30.249632205668384,
          "min": 27.361227214205833,
          "slope_per_step": -0.08752527731194709,
          "std": 3.071823888457596
        },
        "outlet_to_inlet_flux_ratio": {
          "available": true,
          "count": 6,
          "cv": 0.10840240680527055,
          "final": 0.716381192747597,
          "max": 0.8715312530850248,
          "max_abs": 0.8715312530850248,
          "mean": 0.710165974942281,
          "min": 0.6416506245811293,
          "slope_per_step": -0.0024014504572192146,
          "std": 0.07698370091495471
        }
      },
      "name": "250_300",
      "record_count": 6,
      "start_step": 250.0
    },
    {
      "end_step": 400.0,
      "metrics": {
        "flux_imbalance_rel": {
          "available": true,
          "count": 11,
          "cv": 0.44964977909433296,
          "final": 0.12315857710041415,
          "max": 0.28361880725240296,
          "max_abs": 0.28361880725240296,
          "mean": 0.15645875305428672,
          "min": 0.005740117043629117,
          "slope_per_step": -0.001222742887151991,
          "std": 0.07035164374823481
        },
        "inlet_flux": {
          "available": true,
          "count": 11,
          "cv": 0.004262763657727125,
          "final": 42.62274994716527,
          "max": 43.2562783929785,
          "max_abs": 43.2562783929785,
          "mean": 42.96565161134603,
          "min": 42.62274994716527,
          "slope_per_step": -0.003584037591092743,
          "std": 0.18315241821941072
        },
        "midplane_flux": {
          "available": true,
          "count": 11,
          "cv": 0.17834209541141086,
          "final": 54.96521068276907,
          "max": 57.015040515601484,
          "max_abs": 57.015040515601484,
          "mean": 45.908200199821735,
          "min": 30.094100030604615,
          "slope_per_step": 0.25208948689181426,
          "std": 8.187364620202759
        },
        "midplane_to_inlet_flux_ratio": {
          "available": true,
          "count": 11,
          "cv": 0.18075533246027004,
          "final": 1.289574481958658,
          "max": 1.3352707374341433,
          "max_abs": 1.3352707374341433,
          "mean": 1.0689042750085396,
          "min": 0.7002689793802636,
          "slope_per_step": 0.005970306725796511,
          "std": 0.19321014759737248
        },
        "near_outlet_to_outlet_flux_ratio": {
          "available": true,
          "count": 11,
          "cv": 0.005956805033088399,
          "final": 1.004163061884744,
          "max": 1.010395210269098,
          "max_abs": 1.010395210269098,
          "mean": 1.0036604878734643,
          "min": 0.9907887424954328,
          "slope_per_step": 0.00013601643820267768,
          "std": 0.0059786098456766105
        },
        "outlet_flux": {
          "available": true,
          "count": 11,
          "cv": 0.17961102215816158,
          "final": 48.60941651937256,
          "max": 50.578228337254714,
          "max_abs": 50.578228337254714,
          "mean": 43.12667389731021,
          "min": 30.786523335175524,
          "slope_per_step": 0.2191869644879116,
          "std": 7.746025980977593
        },
        "outlet_flux_after_correction": {
          "available": true,
          "count": 11,
          "cv": 0.17961102215816158,
          "final": 48.60941651937256,
          "max": 50.578228337254714,
          "max_abs": 50.578228337254714,
          "mean": 43.12667389731021,
          "min": 30.786523335175524,
          "slope_per_step": 0.2191869644879116,
          "std": 7.746025980977593
        },
        "outlet_to_inlet_flux_ratio": {
          "available": true,
          "count": 11,
          "cv": 0.18068800017619108,
          "final": 1.1404570699832437,
          "max": 1.1779581059757054,
          "max_abs": 1.1779581059757054,
          "mean": 1.0039568790807543,
          "min": 0.716381192747597,
          "slope_per_step": 0.005192574599407643,
          "std": 0.18140296074423157
        }
      },
      "name": "300_400",
      "record_count": 11,
      "start_step": 300.0
    },
    {
      "end_step": 500.0,
      "metrics": {
        "flux_imbalance_rel": {
          "available": true,
          "count": 11,
          "cv": 0.4610363886390531,
          "final": 0.14715617938028439,
          "max": 0.16810119026843742,
          "max_abs": 0.16810119026843742,
          "mean": 0.10270018561574665,
          "min": 0.026156600535798866,
          "slope_per_step": -0.0005062430621851308,
          "std": 0.04734852268884426
        },
        "inlet_flux": {
          "available": true,
          "count": 11,
          "cv": 0.0037227307484699215,
          "final": 42.60692287686617,
          "max": 42.62274994716527,
          "max_abs": 42.62274994716527,
          "mean": 42.4532941686868,
          "min": 42.187918924011164,
          "slope_per_step": 0.0011930283809450256,
          "std": 0.15804218357560917
        },
        "midplane_flux": {
          "available": true,
          "count": 11,
          "cv": 0.1569871494679579,
          "final": 35.095189026892385,
          "max": 54.96521068276907,
          "max_abs": 54.96521068276907,
          "mean": 42.52933893013661,
          "min": 34.325066410093186,
          "slope_per_step": -0.206775044643576,
          "std": 6.676559687398796
        },
        "midplane_to_inlet_flux_ratio": {
          "available": true,
          "count": 11,
          "cv": 0.156974895369559,
          "final": 0.8236968703024468,
          "max": 1.289574481958658,
          "max_abs": 1.289574481958658,
          "mean": 1.0018682973701165,
          "min": 0.8053993411161641,
          "slope_per_step": -0.004885437399676657,
          "std": 0.15726817115375227
        },
        "near_outlet_to_outlet_flux_ratio": {
          "available": true,
          "count": 11,
          "cv": 0.004746456634391589,
          "final": 0.9918117946336654,
          "max": 1.004163061884744,
          "max_abs": 1.004163061884744,
          "mean": 0.9978928625164406,
          "min": 0.9918117946336654,
          "slope_per_step": -0.00014463266081474172,
          "std": 0.004736455197703174
        },
        "outlet_flux": {
          "available": true,
          "count": 11,
          "cv": 0.11556697847525366,
          "final": 36.33705089115611,
          "max": 50.95658037972954,
          "max_abs": 50.95658037972954,
          "mean": 44.03513145904436,
          "min": 36.33705089115611,
          "slope_per_step": -0.15058195000693866,
          "std": 5.089007089482345
        },
        "outlet_flux_after_correction": {
          "available": true,
          "count": 11,
          "cv": 0.11556697847525366,
          "final": 36.33705089115611,
          "max": 50.95658037972954,
          "max_abs": 50.95658037972954,
          "mean": 44.03513145904436,
          "min": 36.33705089115611,
          "slope_per_step": -0.15058195000693866,
          "std": 5.089007089482345
        },
        "outlet_to_inlet_flux_ratio": {
          "available": true,
          "count": 11,
          "cv": 0.11710523793584657,
          "final": 0.8528438206197156,
          "max": 1.2020692760970297,
          "max_abs": 1.2020692760970297,
          "mean": 1.0374656701155318,
          "min": 0.8528438206197156,
          "slope_per_step": -0.0035697112375141474,
          "std": 0.12149266414915186
        }
      },
      "name": "400_500",
      "record_count": 11,
      "start_step": 400.0
    },
    {
      "end_step": 500.0,
      "metrics": {
        "flux_imbalance_rel": {
          "available": true,
          "count": 41,
          "cv": 0.5941572988501203,
          "final": 0.14715617938028439,
          "max": 0.3583493754188707,
          "max_abs": 0.3583493754188707,
          "mean": 0.16838795000146956,
          "min": 0.005740117043629117,
          "slope_per_step": -0.0003332812668164036,
          "std": 0.10004892953178225
        },
        "inlet_flux": {
          "available": true,
          "count": 41,
          "cv": 0.011537499914335761,
          "final": 42.60692287686617,
          "max": 43.76074485117861,
          "max_abs": 43.76074485117861,
          "mean": 42.68151087365078,
          "min": 41.898926254411606,
          "slope_per_step": -0.0010968960484648421,
          "std": 0.49243792804846676
        },
        "midplane_flux": {
          "available": true,
          "count": 41,
          "cv": 0.2616719041255739,
          "final": 35.095189026892385,
          "max": 65.72804967763867,
          "max_abs": 65.72804967763867,
          "mean": 44.95036278724395,
          "min": 26.98942993946515,
          "slope_per_step": -0.032747042772388595,
          "std": 11.762247021673462
        },
        "midplane_to_inlet_flux_ratio": {
          "available": true,
          "count": 41,
          "cv": 0.260037460266374,
          "final": 0.8236968703024468,
          "max": 1.5255159523057769,
          "max_abs": 1.5255159523057769,
          "mean": 1.0527516667335057,
          "min": 0.6329315729213756,
          "slope_per_step": -0.0007378728326915381,
          "std": 0.273754869708573
        },
        "near_outlet_to_outlet_flux_ratio": {
          "available": true,
          "count": 41,
          "cv": 0.01069512238627174,
          "final": 0.9918117946336654,
          "max": 1.0173348052985167,
          "max_abs": 1.0173348052985167,
          "mean": 1.0006175304709648,
          "min": 0.9747990569059142,
          "slope_per_step": -3.1787199456518195e-05,
          "std": 0.010701726950235961
        },
        "outlet_flux": {
          "available": true,
          "count": 41,
          "cv": 0.21935146401201075,
          "final": 36.33705089115611,
          "max": 65.45242040478726,
          "max_abs": 65.45242040478726,
          "mean": 44.379641363644794,
          "min": 27.361227214205833,
          "slope_per_step": -0.018588262443872135,
          "std": 9.734739305443474
        },
        "outlet_flux_after_correction": {
          "available": true,
          "count": 41,
          "cv": 0.21935146401201075,
          "final": 36.33705089115611,
          "max": 65.45242040478726,
          "max_abs": 65.45242040478726,
          "mean": 44.379641363644794,
          "min": 27.361227214205833,
          "slope_per_step": -0.018588262443872135,
          "std": 9.734739305443474
        },
        "outlet_to_inlet_flux_ratio": {
          "available": true,
          "count": 41,
          "cv": 0.21999557319084886,
          "final": 0.8528438206197156,
          "max": 1.5245011266994486,
          "max_abs": 1.5245011266994486,
          "mean": 1.0401470575864384,
          "min": 0.6416506245811293,
          "slope_per_step": -0.0004108716026749017,
          "std": 0.22882774813650342
        }
      },
      "name": "tail_80pct_diagnostic",
      "record_count": 41,
      "start_step": 99.99999999999997
    },
    {
      "end_step": 500.0,
      "metrics": {
        "flux_imbalance_rel": {
          "available": true,
          "count": 11,
          "cv": 0.4610363886390531,
          "final": 0.14715617938028439,
          "max": 0.16810119026843742,
          "max_abs": 0.16810119026843742,
          "mean": 0.10270018561574665,
          "min": 0.026156600535798866,
          "slope_per_step": -0.0005062430621851308,
          "std": 0.04734852268884426
        },
        "inlet_flux": {
          "available": true,
          "count": 11,
          "cv": 0.0037227307484699215,
          "final": 42.60692287686617,
          "max": 42.62274994716527,
          "max_abs": 42.62274994716527,
          "mean": 42.4532941686868,
          "min": 42.187918924011164,
          "slope_per_step": 0.0011930283809450256,
          "std": 0.15804218357560917
        },
        "midplane_flux": {
          "available": true,
          "count": 11,
          "cv": 0.1569871494679579,
          "final": 35.095189026892385,
          "max": 54.96521068276907,
          "max_abs": 54.96521068276907,
          "mean": 42.52933893013661,
          "min": 34.325066410093186,
          "slope_per_step": -0.206775044643576,
          "std": 6.676559687398796
        },
        "midplane_to_inlet_flux_ratio": {
          "available": true,
          "count": 11,
          "cv": 0.156974895369559,
          "final": 0.8236968703024468,
          "max": 1.289574481958658,
          "max_abs": 1.289574481958658,
          "mean": 1.0018682973701165,
          "min": 0.8053993411161641,
          "slope_per_step": -0.004885437399676657,
          "std": 0.15726817115375227
        },
        "near_outlet_to_outlet_flux_ratio": {
          "available": true,
          "count": 11,
          "cv": 0.004746456634391589,
          "final": 0.9918117946336654,
          "max": 1.004163061884744,
          "max_abs": 1.004163061884744,
          "mean": 0.9978928625164406,
          "min": 0.9918117946336654,
          "slope_per_step": -0.00014463266081474172,
          "std": 0.004736455197703174
        },
        "outlet_flux": {
          "available": true,
          "count": 11,
          "cv": 0.11556697847525366,
          "final": 36.33705089115611,
          "max": 50.95658037972954,
          "max_abs": 50.95658037972954,
          "mean": 44.03513145904436,
          "min": 36.33705089115611,
          "slope_per_step": -0.15058195000693866,
          "std": 5.089007089482345
        },
        "outlet_flux_after_correction": {
          "available": true,
          "count": 11,
          "cv": 0.11556697847525366,
          "final": 36.33705089115611,
          "max": 50.95658037972954,
          "max_abs": 50.95658037972954,
          "mean": 44.03513145904436,
          "min": 36.33705089115611,
          "slope_per_step": -0.15058195000693866,
          "std": 5.089007089482345
        },
        "outlet_to_inlet_flux_ratio": {
          "available": true,
          "count": 11,
          "cv": 0.11710523793584657,
          "final": 0.8528438206197156,
          "max": 1.2020692760970297,
          "max_abs": 1.2020692760970297,
          "mean": 1.0374656701155318,
          "min": 0.8528438206197156,
          "slope_per_step": -0.0035697112375141474,
          "std": 0.12149266414915186
        }
      },
      "name": "tail_20pct_hard_gate",
      "record_count": 11,
      "start_step": 400.0
    }
  ],
  "selected96_execution_allowed": false,
  "source_step": 139,
  "step": 140,
  "step139_input_root": "outputs/step139_planeflux_final48",
  "unavailable_fields": [],
  "validation_claim_allowed": false
}
